pyrosper/__init__.py
pyrosper/base_experiment.py
pyrosper/base_experiment_test.py
pyrosper/context.py
pyrosper/context_test.py
pyrosper/pyrosper.py
pyrosper/pyrosper_test.py
pyrosper/symbol.py
pyrosper/symbol_test.py
pyrosper/user_variant.py
pyrosper/variant.py
pyrosper/variant_test.py
pyrosper/version.py
pyrosper/mock/__init__.py
pyrosper/mock/mock_algorithm.py
pyrosper/mock/mock_experiment.py
pyrosper/mock/mock_pyrosper.py
pyrosper/mock/mock_user_variant.py
pyrosper/mock/mock_variant.py
pyrosper-0.1.8.post1.dist-info/licenses/LICENSE
pyrosper-0.1.8.post1.dist-info/METADATA
pyrosper-0.1.8.post1.dist-info/WHEEL
pyrosper-0.1.8.post1.dist-info/top_level.txt
pyrosper-0.1.8.post1.dist-info/RECORD
