Metadata-Version: 2.4
Name: pyrosper
Version: 0.1.8.post1
Summary: A continuously improving, experimentation framework.
Home-page: https://github.com/BKKnights/pyrosper
Author: Robert Plummer
Author-email: Robert Plummer <robertleeplummerjr@gmail.com>
Project-URL: Homepage, https://github.com/BKKnights/pyrosper
Project-URL: Bug Tracker, https://github.com/BKKnights/pyrosper/issues
Requires-Python: >=3.11
License-File: LICENSE
Provides-Extra: dev
Requires-Dist: pytest; extra == "dev"
Requires-Dist: black; extra == "dev"
Requires-Dist: isort; extra == "dev"
Dynamic: author
Dynamic: home-page
Dynamic: license-file
Dynamic: requires-python
